tests/__init__.py
tests/test_core.py
tests/test_helper.py
toolsworks/__init__.py
toolsworks/cli.py
toolsworks/core.py
toolsworks/helper.py
toolsworks-0.1.0.dist-info/METADATA
toolsworks-0.1.0.dist-info/WHEEL
toolsworks-0.1.0.dist-info/entry_points.txt
toolsworks-0.1.0.dist-info/top_level.txt
toolsworks-0.1.0.dist-info/RECORD
