Metadata-Version: 2.1
Name: toolsworks
Version: 0.1.0
Summary: A simple Python package for demonstration purposes.
Home-page: https://github.com/yourusername/toolsworks
Author: Dong H. Ahn
Author-email: donga@nvidia.com
License: MIT
Classifier: Programming Language :: Python :: 3
Classifier: License :: OSI Approved :: MIT License
Classifier: Operating System :: OS Independent
Requires-Python: >=3.6
